{
    "SecretList": [
        {
            "ARN": "arn:aws:secretsmanager:ap-southeast-1:647828570435:secret:flashwire/prod/lending/cobo-mpc-heazdS",
            "Name": "flashwire/prod/lending/cobo-mpc",
            "LastChangedDate": "2024-05-28T12:37:23.067000+05:00",
            "LastAccessedDate": "2024-05-28T05:00:00+05:00",
            "Tags": [
                {
                    "Key": "productLine",
                    "Value": "lending"
                },
                {
                    "Key": "company",
                    "Value": "flashwire"
                },
                {
                    "Key": "env",
                    "Value": "prod"
                }
            ],
            "SecretVersionsToStages": {
                "577ad6ae-d6d8-4078-99ab-f1c126fa1615": [
                    "AWSCURRENT"
                ]
            },
            "CreatedDate": "2024-05-28T12:37:22.804000+05:00"
        },
        {
            "ARN": "arn:aws:secretsmanager:ap-southeast-1:647828570435:secret:flashwire/prod/stellapay/cobo-mpc-WuYRSU",
            "Name": "flashwire/prod/stellapay/cobo-mpc",
            "LastChangedDate": "2024-05-28T12:43:03.083000+05:00",
            "LastAccessedDate": "2024-05-28T05:00:00+05:00",
            "Tags": [
                {
                    "Key": "productLine",
                    "Value": "debitcard"
                },
                {
                    "Key": "company",
                    "Value": "flashwire"
                },
                {
                    "Key": "env",
                    "Value": "prod"
                }
            ],
            "SecretVersionsToStages": {
                "148f5c58-30f6-4b27-b7a2-de586d96cc79": [
                    "AWSCURRENT"
                ]
            },
            "CreatedDate": "2024-05-28T12:43:03.053000+05:00"
        }
    ]
}
